<?xml version='1.0' encoding='utf-8'?>
<bbapi version='1'>
    <schedule teamid='163402' season='51' retrieved='2023-02-24T22:04:51Z'>
        <match id='111999520' start='2020-09-10T16:35:00Z' type='friendly'>
            <awayTeam id='163402'>
                <teamName>Polonia Fordon</teamName>
<score>81</score>
            </awayTeam>
            <homeTeam id='235405'>
                <teamName>GTK2020</teamName>
<score>115</score>
            </homeTeam>
        </match>
    
        <match id='112354860' start='2020-09-12T16:35:00Z' type='league.rs'>
            <awayTeam id='163402'>
                <teamName>Polonia Fordon</teamName>
<score>85</score>
            </awayTeam>
            <homeTeam id='164924'>
                <teamName>Zbikoo Team</teamName>
<score>95</score>
            </homeTeam>
        </match>
    
        <match id='112354867' start='2020-09-15T16:35:00Z' type='league.rs'>
            <awayTeam id='162456'>
                <teamName>KS Goldena</teamName>
<score>50</score>
            </awayTeam>
            <homeTeam id='163402'>
                <teamName>Polonia Fordon</teamName>
<score>0</score>
            </homeTeam>
        </match>
    
        <match id='112355692' start='2020-09-17T16:35:00Z' type='cup'>
            <awayTeam id='165297'>
                <teamName>Fire BC</teamName>
<score>29</score>
            </awayTeam>
            <homeTeam id='163402'>
                <teamName>Polonia Fordon</teamName>
<score>134</score>
            </homeTeam>
        </match>
    
        <match id='112354874' start='2020-09-19T16:35:00Z' type='league.rs'>
            <awayTeam id='163402'>
                <teamName>Polonia Fordon</teamName>
<score>69</score>
            </awayTeam>
            <homeTeam id='56421'>
                <teamName>Nałęczów Warriors</teamName>
<score>86</score>
            </homeTeam>
        </match>
    
        <match id='112354885' start='2020-09-22T16:35:00Z' type='league.rs'>
            <awayTeam id='55897'>
                <teamName>Niewazne</teamName>
<score>61</score>
            </awayTeam>
            <homeTeam id='163402'>
                <teamName>Polonia Fordon</teamName>
<score>91</score>
            </homeTeam>
        </match>
    
        <match id='113006093' start='2020-09-24T16:35:00Z' type='cup'>
            <awayTeam id='164786'>
                <teamName>Gdansk Nuggets</teamName>
<score>72</score>
            </awayTeam>
            <homeTeam id='163402'>
                <teamName>Polonia Fordon</teamName>
<score>116</score>
            </homeTeam>
        </match>
    
        <match id='112354892' start='2020-09-26T16:35:00Z' type='league.rs.tv'>
            <awayTeam id='163402'>
                <teamName>Polonia Fordon</teamName>
<score>64</score>
            </awayTeam>
            <homeTeam id='55719'>
                <teamName>Legendy Wrocław</teamName>
<score>81</score>
            </homeTeam>
        </match>
    
        <match id='112354901' start='2020-09-29T16:35:00Z' type='league.rs'>
            <awayTeam id='163966'>
                <teamName>Pogrążacze</teamName>
<score>60</score>
            </awayTeam>
            <homeTeam id='163402'>
                <teamName>Polonia Fordon</teamName>
<score>73</score>
            </homeTeam>
        </match>
    
        <match id='113019190' start='2020-10-01T16:35:00Z' type='cup'>
            <awayTeam id='163402'>
                <teamName>Polonia Fordon</teamName>
<score>129</score>
            </awayTeam>
            <homeTeam id='56289'>
                <teamName>Kawaleria Przemysl</teamName>
<score>91</score>
            </homeTeam>
        </match>
    
        <match id='112354909' start='2020-10-03T16:35:00Z' type='league.rs'>
            <awayTeam id='163288'>
                <teamName>Chomiczówka´s Boys</teamName>
<score>74</score>
            </awayTeam>
            <homeTeam id='163402'>
                <teamName>Polonia Fordon</teamName>
<score>78</score>
            </homeTeam>
        </match>
    
        <match id='112354920' start='2020-10-06T16:35:00Z' type='league.rs'>
            <awayTeam id='163402'>
                <teamName>Polonia Fordon</teamName>
<score>90</score>
            </awayTeam>
            <homeTeam id='165275'>
                <teamName>Bieszczadzkie Anioły</teamName>
<score>76</score>
            </homeTeam>
        </match>
    
        <match id='113027301' start='2020-10-08T16:35:00Z' type='cup'>
            <awayTeam id='56155'>
                <teamName>MKS Podlasie Sokołów Podlaski</teamName>
<score>69</score>
            </awayTeam>
            <homeTeam id='163402'>
                <teamName>Polonia Fordon</teamName>
<score>121</score>
            </homeTeam>
        </match>
    
        <match id='112354928' start='2020-10-10T16:35:00Z' type='league.rs'>
            <awayTeam id='56224'>
                <teamName>Dudopol Dudowizna</teamName>
<score>53</score>
            </awayTeam>
            <homeTeam id='163402'>
                <teamName>Polonia Fordon</teamName>
<score>84</score>
            </homeTeam>
        </match>
    
        <match id='112354936' start='2020-10-13T16:35:00Z' type='league.rs'>
            <awayTeam id='163402'>
                <teamName>Polonia Fordon</teamName>
<score>72</score>
            </awayTeam>
            <homeTeam id='56049'>
                <teamName>Both teams played hard</teamName>
<score>60</score>
            </homeTeam>
        </match>
    
        <match id='113032859' start='2020-10-15T16:35:00Z' type='cup'>
            <awayTeam id='163402'>
                <teamName>Polonia Fordon</teamName>
<score>97</score>
            </awayTeam>
            <homeTeam id='163814'>
                <teamName>Viking Athletic</teamName>
<score>49</score>
            </homeTeam>
        </match>
    
        <match id='112354944' start='2020-10-17T16:35:00Z' type='league.rs'>
            <awayTeam id='56221'>
                <teamName>Chiki-Cziki-Chiki-Ta</teamName>
<score>40</score>
            </awayTeam>
            <homeTeam id='163402'>
                <teamName>Polonia Fordon</teamName>
<score>126</score>
            </homeTeam>
        </match>
    
        <match id='112354952' start='2020-10-20T16:35:00Z' type='league.rs'>
            <awayTeam id='163402'>
                <teamName>Polonia Fordon</teamName>
<score>50</score>
            </awayTeam>
            <homeTeam id='56364'>
                <teamName>Szerszony</teamName>
<score>76</score>
            </homeTeam>
        </match>
    
        <match id='113038183' start='2020-10-22T16:35:00Z' type='cup'>
            <awayTeam id='163402'>
                <teamName>Polonia Fordon</teamName>
<score>108</score>
            </awayTeam>
            <homeTeam id='165877'>
                <teamName>SanJose Team</teamName>
<score>62</score>
            </homeTeam>
        </match>
    
        <match id='112354960' start='2020-10-24T16:35:00Z' type='league.rs'>
            <awayTeam id='162788'>
                <teamName>Młoty Stargard</teamName>
<score>101</score>
            </awayTeam>
            <homeTeam id='163402'>
                <teamName>Polonia Fordon</teamName>
<score>29</score>
            </homeTeam>
        </match>
    
        <match id='113043580' start='2020-10-27T16:35:00Z' type='cup'>
            <awayTeam id='55897'>
                <teamName>Niewazne</teamName>
<score>59</score>
            </awayTeam>
            <homeTeam id='163402'>
                <teamName>Polonia Fordon</teamName>
<score>90</score>
            </homeTeam>
        </match>
    
        <match id='1049002140' start='2020-10-28T16:35:00Z' type='unknown'>
            <awayTeam id='2140'>
                <teamName>Great 8</teamName>
<score>129</score>
            </awayTeam>
            <homeTeam id='2140'>
                <teamName>Big 8</teamName>
<score>167</score>
            </homeTeam>
        </match>
    
        <match id='113048475' start='2020-10-29T16:35:00Z' type='cup'>
            <awayTeam id='163402'>
                <teamName>Polonia Fordon</teamName>
<score>84</score>
            </awayTeam>
            <homeTeam id='56269'>
                <teamName>vanitas vanitatum</teamName>
<score>34</score>
            </homeTeam>
        </match>
    
        <match id='112354968' start='2020-10-31T16:35:00Z' type='league.rs.tv'>
            <awayTeam id='163402'>
                <teamName>Polonia Fordon</teamName>
<score>83</score>
            </awayTeam>
            <homeTeam id='163885'>
                <teamName>Orzeł Cesarski Poznań</teamName>
<score>69</score>
            </homeTeam>
        </match>
    
        <match id='112354976' start='2020-11-03T17:35:00Z' type='league.rs'>
            <awayTeam id='55528'>
                <teamName>Lame Ducks</teamName>
<score>18</score>
            </awayTeam>
            <homeTeam id='163402'>
                <teamName>Polonia Fordon</teamName>
<score>99</score>
            </homeTeam>
        </match>
    
        <match id='113048939' start='2020-11-05T17:35:00Z' type='cup'>
            <awayTeam id='163402'>
                <teamName>Polonia Fordon</teamName>
<score>92</score>
            </awayTeam>
            <homeTeam id='56429'>
                <teamName>TOP TEN THUNDERS</teamName>
<score>83</score>
            </homeTeam>
        </match>
    
        <match id='112354980' start='2020-11-07T17:35:00Z' type='league.rs'>
            <awayTeam id='164924'>
                <teamName>Zbikoo Team</teamName>
<score>54</score>
            </awayTeam>
            <homeTeam id='163402'>
                <teamName>Polonia Fordon</teamName>
<score>106</score>
            </homeTeam>
        </match>
    
        <match id='112354987' start='2020-11-10T17:35:00Z' type='league.rs'>
            <awayTeam id='163402'>
                <teamName>Polonia Fordon</teamName>
<score>76</score>
            </awayTeam>
            <homeTeam id='162456'>
                <teamName>KS Goldena</teamName>
<score>85</score>
            </homeTeam>
        </match>
    
        <match id='113054363' start='2020-11-12T17:35:00Z' type='cup.semi_or_final'>
            <awayTeam id='56049'>
                <teamName>Both teams played hard</teamName>
<score>83</score>
            </awayTeam>
            <homeTeam id='163402'>
                <teamName>Polonia Fordon</teamName>
<score>72</score>
            </homeTeam>
        </match>
    
        <match id='112354994' start='2020-11-14T17:35:00Z' type='league.rs'>
            <awayTeam id='56421'>
                <teamName>Nałęczów Warriors</teamName>
<score>69</score>
            </awayTeam>
            <homeTeam id='163402'>
                <teamName>Polonia Fordon</teamName>
<score>105</score>
            </homeTeam>
        </match>
    
        <match id='112355005' start='2020-11-17T17:35:00Z' type='league.rs'>
            <awayTeam id='163402'>
                <teamName>Polonia Fordon</teamName>
<score>91</score>
            </awayTeam>
            <homeTeam id='55897'>
                <teamName>Niewazne</teamName>
<score>68</score>
            </homeTeam>
        </match>
    
        <match id='113061959' start='2020-11-19T17:35:00Z' type='friendly'>
            <awayTeam id='171447'>
                <teamName>LMM Bardejov</teamName>
<score>60</score>
            </awayTeam>
            <homeTeam id='163402'>
                <teamName>Polonia Fordon</teamName>
<score>114</score>
            </homeTeam>
        </match>
    
        <match id='112355012' start='2020-11-21T17:35:00Z' type='league.rs.tv'>
            <awayTeam id='55719'>
                <teamName>Legendy Wrocław</teamName>
<score>71</score>
            </awayTeam>
            <homeTeam id='163402'>
                <teamName>Polonia Fordon</teamName>
<score>79</score>
            </homeTeam>
        </match>
    
        <match id='112355021' start='2020-11-24T17:35:00Z' type='league.rs'>
            <awayTeam id='163402'>
                <teamName>Polonia Fordon</teamName>
<score>73</score>
            </awayTeam>
            <homeTeam id='163966'>
                <teamName>Pogrążacze</teamName>
<score>85</score>
            </homeTeam>
        </match>
    
        <match id='113068807' start='2020-11-26T17:35:00Z' type='friendly'>
            <awayTeam id='165522'>
                <teamName>Jagiellonia Włocławek</teamName>
<score>106</score>
            </awayTeam>
            <homeTeam id='163402'>
                <teamName>Polonia Fordon</teamName>
<score>123</score>
            </homeTeam>
        </match>
    
        <match id='112355029' start='2020-11-28T17:35:00Z' type='league.rs'>
            <awayTeam id='163402'>
                <teamName>Polonia Fordon</teamName>
<score>87</score>
            </awayTeam>
            <homeTeam id='163288'>
                <teamName>Chomiczówka´s Boys</teamName>
<score>66</score>
            </homeTeam>
        </match>
    
        <match id='113109974' start='2020-12-01T17:35:00Z' type='league.quarterfinal'>
            <awayTeam id='163402'>
                <teamName>Polonia Fordon</teamName>
<score>69</score>
            </awayTeam>
            <homeTeam id='163966'>
                <teamName>Pogrążacze</teamName>
<score>80</score>
            </homeTeam>
        </match>
    
        <match id='113160424' start='2020-12-05T17:35:00Z' type='friendly'>
            <awayTeam id='56364'>
                <teamName>Szerszony</teamName>
<score>96</score>
            </awayTeam>
            <homeTeam id='163402'>
                <teamName>Polonia Fordon</teamName>
<score>109</score>
            </homeTeam>
        </match>
    
        <match id='113233006' start='2020-12-10T16:30:00Z' type='friendly'>
            <awayTeam id='163402'>
                <teamName>Polonia Fordon</teamName>
<score>121</score>
            </awayTeam>
            <homeTeam id='44930'>
                <teamName>Banov</teamName>
<score>55</score>
            </homeTeam>
        </match>
    
        <match id='113204908' start='2020-12-12T17:35:00Z' type='friendly'>
            <awayTeam id='163402'>
                <teamName>Polonia Fordon</teamName>
<score>82</score>
            </awayTeam>
            <homeTeam id='55528'>
                <teamName>Lame Ducks</teamName>
<score>96</score>
            </homeTeam>
        </match>
    </schedule>
</bbapi>
	